dcvalidator/__init__.py
dcvalidator/nationalcode.py
dcvalidator-1.0.3.dist-info/METADATA
dcvalidator-1.0.3.dist-info/WHEEL
dcvalidator-1.0.3.dist-info/RECORD
